{
  "languageserver": {
    "ccls": {
      "command": "ccls",
      "filetypes": ["c", "cpp", "cuda", "objc", "objcpp"],
      "rootPatterns": [".ccls", "compile_commands.json", ".vim/", ".git/", ".hg/"],
      "initializationOptions": {
         "cache": {
           "directory": ".ccls-cache"
         }
       }
    }
  },
  "codeLens.enable": true,
  "git.addedSign.hlGroup": "GitGutterAdd",
  "git.changedSign.hlGroup": "GitGutterChange",
  "git.removedSign.hlGroup": "GitGutterDelete",
  "git.topRemovedSign.hlGroup": "GitGutterDelete",
  "git.changeRemovedSign.hlGroup": "GitGutterChangeDelete"
}
